bump_version/__init__.py
bump_version/core.py
auto_bump_version-0.0.1.dist-info/METADATA
auto_bump_version-0.0.1.dist-info/WHEEL
auto_bump_version-0.0.1.dist-info/entry_points.txt
auto_bump_version-0.0.1.dist-info/top_level.txt
auto_bump_version-0.0.1.dist-info/RECORD
