Metadata-Version: 2.1
Name: auto-bump-version
Version: 0.0.1
Summary: A command-line tool to automatically bump the version of a Python project
Home-page: https://github.com/dmazin/bump-version
Author: Dmitry Mazin
Author-email: dm@cyberdemon.org
Classifier: Development Status :: 3 - Alpha
Classifier: Intended Audience :: Developers
Classifier: License :: OSI Approved :: MIT License
Classifier: Programming Language :: Python
Classifier: Programming Language :: Python :: 3
Classifier: Programming Language :: Python :: 3.6
Classifier: Programming Language :: Python :: 3.7
Classifier: Programming Language :: Python :: 3.8
Classifier: Programming Language :: Python :: 3.9
Requires-Dist: gitpython
